COPYING
MANIFEST.in
README
health_lifestyle_view.xml
setup.py
./__init__.py
./health_lifestyle.py
./health_lifestyle_view.xml
./tryton.cfg
./data/diets_beliefs.xml
./data/recreational_drugs.xml
./data/vegetarian_types.xml
./doc/index.rst
./locale/ar.po
./locale/de.po
./locale/el.po
./locale/es.po
./locale/fr.po
./locale/it_IT.po
./locale/ja_JP.po
./locale/lo.po
./locale/pt_BR.po
./locale/zh_CN.po
./security/access_rights.xml
./tests/__init__.py
./tests/test_health_lifestyle.py
./view/gnuhealth_diet_belief_form.xml
./view/gnuhealth_diet_belief_tree.xml
./view/gnuhealth_drugs_recreational.xml
./view/gnuhealth_drugs_recreational_tree.xml
./view/gnuhealth_patient.xml
./view/gnuhealth_patient_cage.xml
./view/gnuhealth_patient_cage_tree.xml
./view/gnuhealth_recreational_drugs.xml
./view/gnuhealth_recreational_drugs_tree.xml
./view/gnuhealth_vegetarian_types_form.xml
./view/gnuhealth_vegetarian_types_tree.xml
data/diets_beliefs.xml
data/recreational_drugs.xml
data/vegetarian_types.xml
locale/ar.po
locale/de.po
locale/el.po
locale/es.po
locale/fr.po
locale/it_IT.po
locale/ja_JP.po
locale/lo.po
locale/pt_BR.po
locale/zh_CN.po
security/access_rights.xml
trytond_health_lifestyle.egg-info/PKG-INFO
trytond_health_lifestyle.egg-info/SOURCES.txt
trytond_health_lifestyle.egg-info/dependency_links.txt
trytond_health_lifestyle.egg-info/entry_points.txt
trytond_health_lifestyle.egg-info/not-zip-safe
trytond_health_lifestyle.egg-info/requires.txt
trytond_health_lifestyle.egg-info/top_level.txt
view/gnuhealth_diet_belief_form.xml
view/gnuhealth_diet_belief_tree.xml
view/gnuhealth_drugs_recreational.xml
view/gnuhealth_drugs_recreational_tree.xml
view/gnuhealth_patient.xml
view/gnuhealth_patient_cage.xml
view/gnuhealth_patient_cage_tree.xml
view/gnuhealth_recreational_drugs.xml
view/gnuhealth_recreational_drugs_tree.xml
view/gnuhealth_vegetarian_types_form.xml
view/gnuhealth_vegetarian_types_tree.xml